mem0/memory/__init__.py
mem0/memory/storage.py
mem0_history_db_patch-1.0.3.dist-info/METADATA
mem0_history_db_patch-1.0.3.dist-info/WHEEL
mem0_history_db_patch-1.0.3.dist-info/top_level.txt
mem0_history_db_patch-1.0.3.dist-info/RECORD
