Metadata-Version: 2.4
Name: mem0-history-db-patch
Version: 1.0.3
Summary: SQLAlchemy-based database backend patch for mem0 memory storage
Author-email: Nocyphr <sgu@nocyphr.com>
Maintainer-email: Nocyphr <sgu@nocyphr.com>
License: MIT
Project-URL: Homepage, https://github.com/nocyphr/mem0-history-db-patch
Project-URL: Repository, https://github.com/nocyphr/mem0-history-db-patch
Keywords: mem0,sqlite,postgres,sqlalchemy,patch,memory
Requires-Python: >=3.8
Requires-Dist: mem0ai>=0.1.0
Requires-Dist: sqlalchemy>=2.0.0
